openpluginclient/__init__.py
openpluginclient/openpluginclient.py
openpluginclient/plugins.json
openpluginclient/types.py
tests/__init__.py
tests/test_completion.py
openpluginclient-0.1.7.dist-info/METADATA
openpluginclient-0.1.7.dist-info/WHEEL
openpluginclient-0.1.7.dist-info/top_level.txt
openpluginclient-0.1.7.dist-info/RECORD
