Metadata-Version: 2.1
Name: openpluginclient
Version: 0.1.7
Summary: Python package for accessing ChatGPT plugins via API
Home-page: UNKNOWN
Author: Sebastian Sosa
Author-email: 1sebastian1sosa1@gmail.com
License: UNKNOWN
Keywords: python,openai,chatgpt,chat,plugin
Platform: UNKNOWN
Classifier: Development Status :: 2 - Pre-Alpha
Classifier: Intended Audience :: Developers
Classifier: Programming Language :: Python :: 3.10
Classifier: Programming Language :: Python :: 3
Classifier: Operating System :: MacOS :: MacOS X
Classifier: Operating System :: Microsoft :: Windows
Requires-Dist: requests
